glados/__init__.py
glados/bot.py
glados/configs.py
glados/core.py
glados/datastore.py
glados/errors.py
glados/message_blocks.py
glados/plugin.py
glados/request.py
glados/route_type.py
glados/router.py
glados/utils.py
glados/slack_classes/__init__.py
glados/slack_classes/views.py
glados-0.0.1.dev24.dist-info/LICENSE.md
glados-0.0.1.dev24.dist-info/METADATA
glados-0.0.1.dev24.dist-info/WHEEL
glados-0.0.1.dev24.dist-info/top_level.txt
glados-0.0.1.dev24.dist-info/RECORD
